cicd_demo/__init__.py
cicd_demo/validator.py
cicd_demo-0.1.6.dist-info/METADATA
cicd_demo-0.1.6.dist-info/WHEEL
cicd_demo-0.1.6.dist-info/RECORD
